{
    "Problem": [
        {
            "Lower bound": 4246.03132013232,
            "Name": "unknown",
            "Number of constraints": 832,
            "Number of nonzeros": 219236,
            "Number of objectives": 1,
            "Number of variables": 11129,
            "Sense": "maximize",
            "Upper bound": 4246.03132013232
        }
    ],
    "Solution": [
        {
            "number of solutions": 1,
            "number of solutions displayed": 1
        },
        {
            "Constraint": "No values",
            "Gap": 0.0,
            "Message": null,
            "Objective": {
                "objective": {
                    "Value": 4246.0313201323215
                }
            },
            "Problem": {},
            "Status": "optimal",
            "Variable": {
                "f[0,48]": {
                    "Value": 0.921658986175112
                },
                "f[0,49]": {
                    "Value": 3.2258064516129
                },
                "f[0,51]": {
                    "Value": 0.614439324116747
                },
                "f[1,23]": {
                    "Value": 1.22887864823344
                },
                "f[1,27]": {
                    "Value": 1.53609831029186
                },
                "f[1,29]": {
                    "Value": 1.99692780337946
                },
                "f[10,68]": {
                    "Value": 1.84331797235022
                },
                "f[10,69]": {
                    "Value": 2.91858678955454
                },
                "f[100,72]": {
                    "Value": 0.460829493087551
                },
                "f[100,73]": {
                    "Value": 3.2258064516129
                },
                "f[100,74]": {
                    "Value": 1.07526881720431
                },
                "f[103,27]": {
                    "Value": 1.68970814132104
                },
                "f[103,35]": {
                    "Value": 2.61136712749612
                },
                "f[103,9]": {
                    "Value": 0.4608294930876
                },
                "f[11,36]": {
                    "Value": 0.307219662058371
                },
                "f[11,37]": {
                    "Value": 3.2258064516129
                },
                "f[11,38]": {
                    "Value": 1.22887864823349
                },
                "f[12,29]": {
                    "Value": 1.22887864823345
                },
                "f[12,35]": {
                    "Value": 0.614439324116783
                },
                "f[12,36]": {
                    "Value": 2.91858678955453
                },
                "f[13,23]": {
                    "Value": 1.99692780337946
                },
                "f[13,9]": {
                    "Value": 2.7649769585253
                },
                "f[14,38]": {
                    "Value": 1.99692780337941
                },
                "f[14,39]": {
                    "Value": 2.76497695852535
                },
                "f[15,65]": {
                    "Value": 1.68970814132104
                },
                "f[15,66]": {
                    "Value": 3.07219662058372
                },
                "f[16,78]": {
                    "Value": 2.30414746543778
                },
                "f[16,79]": {
                    "Value": 2.45775729646698
                },
                "f[17,59]": {
                    "Value": 1.38248847926267
                },
                "f[17,60]": {
                    "Value": 3.2258064516129
                },
                "f[17,61]": {
                    "Value": 0.153609831029191
                },
                "f[2,39]": {
                    "Value": 0.460829493087556
                },
                "f[2,40]": {
                    "Value": 3.2258064516129
                },
                "f[2,41]": {
                    "Value": 1.0752688172043
                },
                "f[20,66]": {
                    "Value": 0.15360983102918
                },
                "f[20,67]": {
                    "Value": 3.2258064516129
                },
                "f[20,68]": {
                    "Value": 1.38248847926268
                },
                "f[21,86]": {
                    "Value": 0.921658986175107
                },
                "f[21,89]": {
                    "Value": 3.2258064516129
                },
                "f[21,90]": {
                    "Value": 0.614439324116752
                },
                "f[22,53]": {
                    "Value": 1.0752688172043
                },
                "f[22,54]": {
                    "Value": 3.2258064516129
                },
                "f[22,55]": {
                    "Value": 0.460829493087561
                },
                "f[24,45]": {
                    "Value": 0.768049155145927
                },
                "f[24,46]": {
                    "Value": 3.2258064516129
                },
                "f[24,47]": {
                    "Value": 0.768049155145932
                },
                "f[25,102]": {
                    "Value": 1.22887864823348
                },
                "f[26,74]": {
                    "Value": 2.15053763440859
                },
                "f[26,75]": {
                    "Value": 2.61136712749617
                },
                "f[3,44]": {
                    "Value": 2.30414746543779
                },
                "f[3,45]": {
                    "Value": 2.45775729646698
                },
                "f[33,101]": {
                    "Value": 2.76497695852534
                },
                "f[33,102]": {
                    "Value": 1.99692780337943
                },
                "f[4,47]": {
                    "Value": 2.45775729646697
                },
                "f[4,48]": {
                    "Value": 2.30414746543779
                },
                "f[5,58]": {
                    "Value": 2.91858678955453
                },
                "f[5,59]": {
                    "Value": 1.84331797235023
                },
                "f[6,42]": {
                    "Value": 0.614439324116741
                },
                "f[6,43]": {
                    "Value": 3.2258064516129
                },
                "f[6,44]": {
                    "Value": 0.921658986175117
                },
                "f[7,41]": {
                    "Value": 2.1505376344086
                },
                "f[7,42]": {
                    "Value": 2.61136712749616
                },
                "f[77,90]": {
                    "Value": 2.61136712749615
                },
                "f[77,91]": {
                    "Value": 2.15053763440861
                },
                "f[8,64]": {
                    "Value": 3.2258064516129
                },
                "f[8,65]": {
                    "Value": 1.53609831029186
                },
                "f[84,51]": {
                    "Value": 2.61136712749616
                },
                "f[84,53]": {
                    "Value": 2.15053763440861
                },
                "f[85,101]": {
                    "Value": 0.460829493087567
                },
                "f[85,91]": {
                    "Value": 1.07526881720429
                },
                "f[85,92]": {
                    "Value": 3.2258064516129
                },
                "f[87,69]": {
                    "Value": 0.307219662058365
                },
                "f[87,70]": {
                    "Value": 3.2258064516129
                },
                "f[87,71]": {
                    "Value": 1.22887864823349
                },
                "f[88,62]": {
                    "Value": 1.53609831029185
                },
                "f[88,63]": {
                    "Value": 3.2258064516129
                },
                "f[88,64]": {
                    "Value": 5.32907051820075e-15
                },
                "f[93,71]": {
                    "Value": 1.99692780337941
                },
                "f[93,72]": {
                    "Value": 2.76497695852535
                },
                "f[94,75]": {
                    "Value": 0.614439324116736
                },
                "f[94,76]": {
                    "Value": 3.2258064516129
                },
                "f[94,78]": {
                    "Value": 0.921658986175123
                },
                "f[95,83]": {
                    "Value": 2.45775729646697
                },
                "f[95,86]": {
                    "Value": 2.3041474654378
                },
                "f[96,56]": {
                    "Value": 1.22887864823348
                },
                "f[96,57]": {
                    "Value": 3.2258064516129
                },
                "f[96,58]": {
                    "Value": 0.307219662058376
                },
                "f[97,61]": {
                    "Value": 3.07219662058371
                },
                "f[97,62]": {
                    "Value": 1.68970814132105
                },
                "f[98,55]": {
                    "Value": 2.76497695852534
                },
                "f[98,56]": {
                    "Value": 1.99692780337942
                },
                "f[99,79]": {
                    "Value": 0.768049155145921
                },
                "f[99,81]": {
                    "Value": 3.2258064516129
                },
                "f[99,83]": {
                    "Value": 0.768049155145937
                },
                "s[100]": {
                    "Value": 6.45161290322581
                },
                "s[101]": {
                    "Value": 3.2258064516129
                },
                "s[10]": {
                    "Value": 47.6190476190476
                },
                "s[11]": {
                    "Value": 52.3809523809524
                },
                "s[12]": {
                    "Value": 57.1428571428571
                },
                "s[13]": {
                    "Value": 59.1397849462366
                },
                "s[14]": {
                    "Value": 63.9016897081414
                },
                "s[15]": {
                    "Value": 68.6635944700461
                },
                "s[16]": {
                    "Value": 73.4254992319509
                },
                "s[17]": {
                    "Value": 78.1874039938557
                },
                "s[18]": {
                    "Value": 78.1874039938557
                },
                "s[19]": {
                    "Value": 78.1874039938557
                },
                "s[1]": {
                    "Value": 9.52380952380952
                },
                "s[20]": {
                    "Value": 82.9493087557604
                },
                "s[21]": {
                    "Value": 87.7112135176652
                },
                "s[22]": {
                    "Value": 92.4731182795699
                },
                "s[23]": {
                    "Value": 89.247311827957
                },
                "s[24]": {
                    "Value": 94.0092165898618
                },
                "s[25]": {
                    "Value": 95.2380952380953
                },
                "s[26]": {
                    "Value": 100.0
                },
                "s[27]": {
                    "Value": 98.4639016897082
                },
                "s[28]": {
                    "Value": 98.4639016897082
                },
                "s[29]": {
                    "Value": 95.2380952380953
                },
                "s[2]": {
                    "Value": 14.2857142857143
                },
                "s[30]": {
                    "Value": 95.2380952380953
                },
                "s[31]": {
                    "Value": 95.2380952380953
                },
                "s[32]": {
                    "Value": 95.2380952380953
                },
                "s[33]": {
                    "Value": 100.0
                },
                "s[34]": {
                    "Value": 100.0
                },
                "s[35]": {
                    "Value": 99.3855606758832
                },
                "s[36]": {
                    "Value": 96.1597542242703
                },
                "s[37]": {
                    "Value": 92.9339477726574
                },
                "s[38]": {
                    "Value": 89.7081413210445
                },
                "s[39]": {
                    "Value": 86.4823348694316
                },
                "s[3]": {
                    "Value": 19.0476190476191
                },
                "s[40]": {
                    "Value": 83.2565284178187
                },
                "s[41]": {
                    "Value": 80.0307219662058
                },
                "s[42]": {
                    "Value": 76.8049155145929
                },
                "s[43]": {
                    "Value": 73.57910906298
                },
                "s[44]": {
                    "Value": 70.3533026113671
                },
                "s[45]": {
                    "Value": 67.1274961597542
                },
                "s[46]": {
                    "Value": 63.9016897081413
                },
                "s[47]": {
                    "Value": 60.6758832565284
                },
                "s[48]": {
                    "Value": 57.4500768049155
                },
                "s[49]": {
                    "Value": 54.2242703533026
                },
                "s[4]": {
                    "Value": 23.8095238095238
                },
                "s[50]": {
                    "Value": 54.2242703533026
                },
                "s[51]": {
                    "Value": 53.6098310291858
                },
                "s[52]": {
                    "Value": 53.6098310291858
                },
                "s[53]": {
                    "Value": 52.5345622119816
                },
                "s[54]": {
                    "Value": 49.3087557603687
                },
                "s[55]": {
                    "Value": 48.8479262672811
                },
                "s[56]": {
                    "Value": 48.8479262672811
                },
                "s[57]": {
                    "Value": 48.8479262672811
                },
                "s[58]": {
                    "Value": 45.9293394777266
                },
                "s[59]": {
                    "Value": 42.7035330261137
                },
                "s[5]": {
                    "Value": 28.5714285714286
                },
                "s[60]": {
                    "Value": 39.4777265745008
                },
                "s[61]": {
                    "Value": 39.3241167434716
                },
                "s[62]": {
                    "Value": 39.3241167434716
                },
                "s[63]": {
                    "Value": 39.3241167434716
                },
                "s[64]": {
                    "Value": 36.0983102918587
                },
                "s[65]": {
                    "Value": 32.8725038402458
                },
                "s[66]": {
                    "Value": 29.6466973886329
                },
                "s[67]": {
                    "Value": 26.42089093702
                },
                "s[68]": {
                    "Value": 23.1950844854071
                },
                "s[69]": {
                    "Value": 20.2764976958525
                },
                "s[6]": {
                    "Value": 33.3333333333333
                },
                "s[70]": {
                    "Value": 20.2764976958525
                },
                "s[71]": {
                    "Value": 20.2764976958525
                },
                "s[72]": {
                    "Value": 20.2764976958525
                },
                "s[73]": {
                    "Value": 20.2764976958525
                },
                "s[74]": {
                    "Value": 18.1259600614439
                },
                "s[75]": {
                    "Value": 15.5145929339478
                },
                "s[76]": {
                    "Value": 15.5145929339478
                },
                "s[77]": {
                    "Value": 20.2764976958525
                },
                "s[78]": {
                    "Value": 17.9723502304147
                },
                "s[79]": {
                    "Value": 15.5145929339478
                },
                "s[7]": {
                    "Value": 38.0952380952381
                },
                "s[80]": {
                    "Value": 15.5145929339478
                },
                "s[81]": {
                    "Value": 15.5145929339478
                },
                "s[82]": {
                    "Value": 15.5145929339478
                },
                "s[83]": {
                    "Value": 15.5145929339478
                },
                "s[84]": {
                    "Value": 15.5145929339478
                },
                "s[85]": {
                    "Value": 20.2764976958525
                },
                "s[86]": {
                    "Value": 19.3548387096774
                },
                "s[87]": {
                    "Value": 19.3548387096774
                },
                "s[88]": {
                    "Value": 19.3548387096774
                },
                "s[89]": {
                    "Value": 16.1290322580645
                },
                "s[8]": {
                    "Value": 42.8571428571429
                },
                "s[90]": {
                    "Value": 12.9032258064516
                },
                "s[91]": {
                    "Value": 9.67741935483871
                },
                "s[92]": {
                    "Value": 6.45161290322581
                },
                "s[93]": {
                    "Value": 6.45161290322581
                },
                "s[94]": {
                    "Value": 6.45161290322581
                },
                "s[95]": {
                    "Value": 6.45161290322581
                },
                "s[96]": {
                    "Value": 6.45161290322581
                },
                "s[97]": {
                    "Value": 6.45161290322581
                },
                "s[98]": {
                    "Value": 6.45161290322581
                },
                "s[99]": {
                    "Value": 6.45161290322581
                },
                "s[9]": {
                    "Value": 42.8571428571429
                }
            }
        }
    ],
    "Solver": [
        {
            "Error rc": 0,
            "Statistics": {
                "Branch and bound": {
                    "Number of bounded subproblems": "1",
                    "Number of created subproblems": "1"
                }
            },
            "Status": "ok",
            "Termination condition": "optimal",
            "Time": 1.9129915237426758
        }
    ]
}